_pfutil.cpython-310-x86_64-linux-gnu.so
pfutils-0.0.32.dist-info/METADATA
pfutils-0.0.32.dist-info/WHEEL
pfutils-0.0.32.dist-info/top_level.txt
pfutils-0.0.32.dist-info/LICENSE
pfutils-0.0.32.dist-info/entry_points.txt
pfutils-0.0.32.dist-info/RECORD
pfutils/__main__.py
pfutils/main.py
pfutils/__init__.py
pfutils/utils/chunk.py
pfutils/utils/bulk_pool.py
pfutils/utils/__init__.py
pfutils/utils/file_manager/file_manager.py
pfutils/utils/file_manager/__init__.py
pfutils/commands/main.py
pfutils/commands/scp.py
pfutils/commands/cp.py
pfutils/commands/du.py
pfutils/commands/rm.py
pfutils/commands/mdtest.py
pfutils/commands/__init__.py
